{"type":"Sprite","props":{"y":0,"x":0,"width":750,"presetID":1,"isPresetRoot":true,"height":1334,"enUrl":"item/buy_item_mark_en.png"},"compId":216,"child":[{"type":"Text","props":{"y":282,"x":186,"text":"Watch videos to upgrade!","presetID":3,"fontSize":30,"color":"#ffffff","bold":true,"runtime":"Laya.Text"},"compId":218},{"type":"Image","props":{"y":422,"x":151,"skin":"","presetID":7,"name":"curr_gun"},"compId":223,"child":[{"type":"Image","props":{"y":1,"x":2,"skin":"item/item_level_4.png","presetID":4,"name":"gun_bg"},"compId":220},{"type":"Image","props":{"y":5,"x":6,"skin":"icon/gun_3.png","presetID":6,"name":"gun_icon"},"compId":222},{"type":"Image","props":{"y":98,"x":100,"skin":"item/item_level_mark_4.png","presetID":5,"name":"level_bg"},"compId":221},{"type":"Text","props":{"y":107,"x":67,"width":100,"text":"1","presetID":8,"name":"level","fontSize":20,"color":"#ffffff","bold":false,"align":"center","runtime":"Laya.Text"},"compId":224},{"type":"Text","props":{"y":192,"x":-33,"width":200,"text":"激光枪","presetID":26,"name":"weapon_name","height":27,"fontSize":27,"font":"Arial","color":"#DAAC72","align":"center","runtime":"Laya.Text"},"compId":242},{"type":"Text","props":{"y":253,"x":-14,"text":"秒伤","presetID":27,"name":"weapon_atk_name","fontSize":24,"font":"Arial","color":"#A59DC3","align":"center","runtime":"Laya.Text"},"compId":243},{"type":"Text","props":{"y":296,"x":-14,"text":"攻速","presetID":28,"name":"weapon_atk_speed_name","fontSize":24,"font":"Arial","color":"#A59DC3","align":"center","runtime":"Laya.Text"},"compId":244},{"type":"Text","props":{"y":249,"x":68,"text":"4500","presetID":29,"name":"weapon_atk","fontSize":32,"font":"Arial","color":"#ffffff","bold":false,"align":"left","runtime":"Laya.Text"},"compId":245},{"type":"Text","props":{"y":292,"x":68,"text":"10/S","presetID":30,"name":"weapon_atk_speed","fontSize":32,"font":"Arial","color":"#ffffff","bold":false,"align":"left","runtime":"Laya.Text"},"compId":246}]},{"type":"Image","props":{"y":422,"x":480,"skin":"","presetID":9,"name":"up_gun"},"compId":225,"child":[{"type":"Image","props":{"y":0,"x":2,"skin":"item/item_level_4.png","presetID":10,"name":"gun_bg"},"compId":226},{"type":"Image","props":{"y":4,"x":6,"skin":"icon/gun_3.png","presetID":11,"name":"gun_icon"},"compId":227},{"type":"Image","props":{"y":97,"x":100,"skin":"item/item_level_mark_4.png","presetID":12,"name":"level_bg"},"compId":228},{"type":"Text","props":{"y":106,"x":67,"width":100,"text":"1","presetID":13,"name":"level","fontSize":20,"color":"#ffffff","bold":false,"align":"center","runtime":"Laya.Text"},"compId":229},{"type":"Text","props":{"y":191,"x":-33,"width":200,"text":"激光枪","presetID":21,"name":"weapon_name","height":27,"fontSize":27,"font":"Arial","color":"#DAAC72","align":"center","runtime":"Laya.Text"},"compId":237},{"type":"Text","props":{"y":252,"x":-14,"text":"秒伤","presetID":22,"name":"weapon_atk_name","fontSize":24,"font":"Arial","color":"#A59DC3","align":"center","runtime":"Laya.Text"},"compId":238},{"type":"Text","props":{"y":295,"x":-14,"text":"攻速","presetID":23,"name":"weapon_atk_speed_name","fontSize":24,"font":"Arial","color":"#A59DC3","align":"center","runtime":"Laya.Text"},"compId":239},{"type":"Text","props":{"y":248,"x":68,"text":"4500","presetID":24,"name":"weapon_atk","fontSize":32,"font":"Arial","color":"#ffffff","bold":false,"align":"left","runtime":"Laya.Text"},"compId":240},{"type":"Text","props":{"y":291,"x":68,"text":"10/S","presetID":25,"name":"weapon_atk_speed","fontSize":32,"font":"Arial","color":"#ffffff","bold":false,"align":"left","runtime":"Laya.Text"},"compId":241}]},{"type":"Button","props":{"y":869,"x":375,"width":292,"stateNum":1,"skin":"common/button_purple.png","sizeGrid":"22,25,35,25","presetID":31,"pivotY":53,"pivotX":146,"name":"up_btn","height":105},"compId":247},{"type":"Sprite","props":{"y":459,"x":345,"texture":"perk/perk_levelup_mark.png","scaleY":2,"scaleX":2,"presetID":15},"compId":231},{"type":"Sprite","props":{"y":844.5,"x":251,"texture":"offline_speedup/video.png","presetID":33},"compId":254},{"type":"Button","props":{"y":977,"x":375,"width":200,"stateNum":1,"skin":"common/button_orange.png","sizeGrid":"20,20,20,20","presetID":34,"pivotY":25,"pivotX":100,"name":"close_btn","labelSize":30,"labelColors":"#000000","labelBold":true,"label":"不，谢谢","height":80},"compId":255},{"type":"Text","props":{"y":849,"x":321,"text":"Free","presetID":32,"fontSize":35,"color":"#770C80","bold":true,"runtime":"Laya.Text"},"compId":248},{"type":"Script","props":{"presetID":35,"runtime":"popp/WeaponLevelUpPopp.ts"},"compId":256}],"loadList":["item/buy_item_mark_en.png","item/item_level_4.png","icon/gun_3.png","item/item_level_mark_4.png","common/button_purple.png","perk/perk_levelup_mark.png","offline_speedup/video.png","common/button_orange.png"],"loadList3D":[]}